{
    "cells": [
        {
            "x": 0,
            "z": 0,
            "prefabGuid": "3f3759aa513dae9498996046c2861a3e"
        },
        {
            "x": 1,
            "z": 0,
            "prefabGuid": "3f3759aa513dae9498996046c2861a3e"
        },
        {
            "x": 0,
            "z": 1,
            "prefabGuid": "3f3759aa513dae9498996046c2861a3e"
        },
        {
            "x": 0,
            "z": -1,
            "prefabGuid": "3f3759aa513dae9498996046c2861a3e"
        }
    ]
}